prometheus_metrics/__init__.py
prometheus_metrics/exporter.py
prometheus_metrics/metrics.py
prometheus_metrics-0.1.6.6.dist-info/LICENSE
prometheus_metrics-0.1.6.6.dist-info/METADATA
prometheus_metrics-0.1.6.6.dist-info/WHEEL
prometheus_metrics-0.1.6.6.dist-info/entry_points.txt
prometheus_metrics-0.1.6.6.dist-info/top_level.txt
prometheus_metrics-0.1.6.6.dist-info/RECORD
