Metadata-Version: 2.1
Name: prometheus-metrics
Version: 0.1.6.6
Summary: Manage prometheus metrics
Home-page: https://github.com/dr1s/prometheus_metrics
Author: Daniel Schmitz
License: MIT
Platform: UNKNOWN
Requires-Dist: prometheus-client
